{
  "id": "ep-006",
  "title": "Episode 6: Q&A Session",
  "description": "Exploring fascinating topics with our expert guests. This episode covers important developments in the industry.",
  "longDescription": "In this episode, we dive deep into important topics and explore various perspectives. Our hosts discuss the latest developments and share insights from industry experts. Whether you're interested in business, technology, or creative pursuits, this episode has something for you.",
  "coverImage": "/images/episodes/ep-006.jpg",
  "audioFile": "/audio/episodes/ep-006.mp3",
  "duration": "00:19:55",
  "publishDate": "2024-01-05",
  "isFeatured": false,
  "hosts": [
    "host-001",
    "host-002"
  ],
  "tags": [
    "podcast",
    "discussion",
    "insights"
  ]
}